src/rng_control_path.v
//////////////////////////////////////////////////////////////////////////////////
// Company: 
// Engineer: 
// 
// Create Date:    20:47:20 04/02/2026 
// Design Name: 
// Module Name:    rng_control_path
// Project Name: 
// Target Devices: 
// Tool versions: 
// Description: 
//
// Dependencies: 
//
// Revision: 
// Revision 0.01 - File Created
// Additional Comments: 
//
//////////////////////////////////////////////////////////////////////////////////

module rng_control_path(
    input clk_i,
    input rst_i,
    input req_num,

    output state_o
);

//States:
localparam IDLE = 0;
localparam SEND = 1;

reg next_state;

always@(posedge clk_i or negedge rst_i)
    begin
        if(!rst_i)
            begin
                next_state <= IDLE;
            end
        else 
        if(req_num)
            begin 
                next_state <= SEND;
            end
        else
            begin
                next_state <= IDLE;
            end
    end

assign state_o = next_state;

endmodule

testbenchs/testbench_control_path.v
`timescale 1ns / 1ps

////////////////////////////////////////////////////////////////////////////////
// Company: 
// Engineer:
//
// Create Date:   20:58:55 01/30/2026
// Design Name:   seed_random_1_control_path
// Module Name:   /home/matheus/ISE_projects/seed_random_1/testbench_control_path.v
// Project Name:  seed_random_1
// Target Device:  
// Tool versions:  
// Description: 
//
// Verilog Test Fixture created by ISE for module: seed_random_1_control_path
//
// Dependencies:
// 
// Revision:
// Revision 0.01 - File Created
// Additional Comments:
// 
////////////////////////////////////////////////////////////////////////////////

module testbench_control_path;

	// Inputs
	reg clk_i;
	reg rst_i;
	reg req_num;

	// Outputs
	wire state_o;

	// Instantiate the Unit Under Test (UUT)
	rng_control_path uut (
		.clk_i(clk_i), 
		.rst_i(rst_i), 
		.req_num(req_num), 
		.state_o(state_o)
	);

    initial 
        begin: Clock_generator
          clk_i = 0;
          forever #5 clk_i = ~clk_i;
        end

		//States:
		localparam IDLE = 0;
		localparam SEND = 1;

	initial 
        begin
			rst_i = 1'b0;
			#25;
			rst_i = 1'b1;
			#25;
			req_num = 1'b1;
			#50;
			req_num = 1'b0;
			#50;
			req_num = 1'b1;
			#50;
			req_num = 1'b0;
			#50;
			req_num = 1'b1;
			#50;
			req_num = 1'b0;
			#50;
			$finish;
        end
      
    initial 
        begin: Wavedump
            $dumpfile("../waveforms/control_path.vcd");
            $dumpvars(0);
        end

endmodule

waveforms/control_path.vcd
$date
	Sat Feb  7 18:07:10 2026
$end
$version
	Icarus Verilog
$end
$timescale
	1ps
$end
$scope module testbench_control_path $end
$var wire 1 ! state_o $end
$var parameter 32 " IDLE $end
$var parameter 32 # SEND $end
$var reg 1 $ clk_i $end
$var reg 1 % req_num $end
$var reg 1 & rst_i $end
$scope module uut $end
$var wire 1 $ clk_i $end
$var wire 1 % req_num $end
$var wire 1 & rst_i $end
$var wire 1 ! state_o $end
$var parameter 32 ' IDLE $end
$var parameter 32 ( SEND $end
$var reg 1 ) next_state $end
$upscope $end
$scope begin Clock_generator $end
$upscope $end
$scope begin Wavedump $end
$upscope $end
$upscope $end
$enddefinitions $end
$comment Show the parameter values. $end
$dumpall
b1 (
b0 '
b1 #
b0 "
$end
#0
$dumpvars
0)
0&
x%
0$
0!
$end
#5000
1$
#10000
0$
#15000
1$
#20000
0$
#25000
1$
1&
#30000
0$
#35000
1$
#40000
0$
#45000
1$
#50000
0$
1%
#55000
1!
1)
1$
#60000
0$
#65000
1$
#70000
0$
#75000
1$
#80000
0$
#85000
1$
#90000
0$
#95000
1$
#100000
0$
0%
#105000
0!
0)
1$
#110000
0$
#115000
1$
#120000
0$
#125000
1$
#130000
0$
#135000
1$
#140000
0$
#145000
1$
#150000
0$
1%
#155000
1!
1)
1$
#160000
0$
#165000
1$
#170000
0$
#175000
1$
#180000
0$
#185000
1$
#190000
0$
#195000
1$
#200000
0$
0%
#205000
0!
0)
1$
#210000
0$
#215000
1$
#220000
0$
#225000
1$
#230000
0$
#235000
1$
#240000
0$
#245000
1$
#250000
0$
1%
#255000
1!
1)
1$
#260000
0$
#265000
1$
#270000
0$
#275000
1$
#280000
0$
#285000
1$
#290000
0$
#295000
1$
#300000
0$
0%
#305000
0!
0)
1$
