src/rng_data_path_counter.v
//////////////////////////////////////////////////////////////////////////////////
// Company: 
// Engineer: 
// 
// Create Date:    21:11:06 01/30/2026 
// Design Name: 
// Module Name:    rng_data_path_counter
// Project Name: 
// Target Devices: 
// Tool versions: 
// Description: 
//
// Dependencies: 
//
// Revision: 
// Revision 0.01 - File Created
// Additional Comments: 
//
//////////////////////////////////////////////////////////////////////////////////

module rng_data_path_counter(
    input clk_i,
    input rst_i,
    input req_num,
    output reg [7:0] next_num_o
);

//States:
localparam IDLE = 0;
localparam SEND = 1;

reg [7:0] num_counter;
reg state;

always@(*)
    begin
        state = req_num;
        next_num_o = num_counter;
    end

//Counter:
always@(posedge clk_i or negedge rst_i)
    begin
        if(!rst_i)
            begin
                num_counter    <= 0;
                next_num_o <= 0;
            end
        else 
        if(state == 1)
            begin 
                if(num_counter == 52) 
                    begin
                        num_counter <= 1'b0;
                    end
                else
                    begin
                        num_counter <= num_counter + 1'b1;
                    end
            end
        else
            begin
                num_counter <= num_counter;
            end
    end

endmodule

testbenchs/testbench_data_path_counter.v
`timescale 1ns / 1ps

////////////////////////////////////////////////////////////////////////////////
// Company: 
// Engineer:
//
// Create Date:   09:35:42 01/31/2026
// Design Name:   seed_random_1_data_path_counter
// Module Name:   /home/matheus/ISE_projects/seed_random_1/tb1.v
// Project Name:  seed_random_1
// Target Device:  
// Tool versions:  
// Description: 
//
// Verilog Test Fixture created by ISE for module: seed_random_1_data_path_counter
//
// Dependencies:
// 
// Revision:
// Revision 0.01 - File Created
// Additional Comments:
// 
////////////////////////////////////////////////////////////////////////////////

module testbench_data_path_counter;

	// Inputs
	reg clk_i;
	reg rst_i;
	reg req_num;

	// Outputs
	wire [7:0] next_num_o;

	// Instantiate the Unit Under Test (UUT)
	rng_data_path_counter uut (
		.clk_i(clk_i), 
		.rst_i(rst_i), 
		.req_num(req_num), 
		.next_num_o(next_num_o)
	);

    initial 
        begin: Clock_generator
          clk_i = 0;
          forever #5 clk_i = ~clk_i;
        end

	initial 
        begin
            // Initialize Inputs
			rst_i = 0; req_num = 0;
			#10;
			rst_i = 1;
			#10;
            req_num = 1;
			#150;
            req_num = 0;
			#150;
            req_num = 1;
			#150;
			rst_i = 0;
			#10;
			rst_i = 1;
			#10;
            req_num = 1;
			#150;
            req_num = 0;
			#150;
            req_num = 1;
			#150;
			$finish;
        end
      
    initial 
        begin: Wavedump
            $dumpfile("../waveforms/data_path_counter.vcd");
            $dumpvars(0);
        end

endmodule

waveforms/data_path_counter.vcd
$date
	Sat Feb  7 18:43:31 2026
$end
$version
	Icarus Verilog
$end
$timescale
	1ps
$end
$scope module testbench_data_path_counter $end
$var wire 8 ! next_num_o [7:0] $end
$var reg 1 " clk_i $end
$var reg 1 # req_num $end
$var reg 1 $ rst_i $end
$scope module uut $end
$var wire 1 " clk_i $end
$var wire 1 # req_num $end
$var wire 1 $ rst_i $end
$var parameter 32 % IDLE $end
$var parameter 32 & SEND $end
$var reg 8 ' next_num_o [7:0] $end
$var reg 8 ( num_counter [7:0] $end
$var reg 1 ) state $end
$upscope $end
$scope begin Clock_generator $end
$upscope $end
$scope begin Wavedump $end
$upscope $end
$upscope $end
$enddefinitions $end
$comment Show the parameter values. $end
$dumpall
b1 &
b0 %
$end
#0
$dumpvars
0)
b0 (
b0 '
0$
0#
0"
b0 !
$end
#5000
1"
#10000
0"
1$
#15000
1"
#20000
1)
0"
1#
#25000
b1 !
b1 '
b1 (
1"
#30000
0"
#35000
b10 !
b10 '
b10 (
1"
#40000
0"
#45000
b11 !
b11 '
b11 (
1"
#50000
0"
#55000
b100 !
b100 '
b100 (
1"
#60000
0"
#65000
b101 !
b101 '
b101 (
1"
#70000
0"
#75000
b110 !
b110 '
b110 (
1"
#80000
0"
#85000
b111 !
b111 '
b111 (
1"
#90000
0"
#95000
b1000 !
b1000 '
b1000 (
1"
#100000
0"
#105000
b1001 !
b1001 '
b1001 (
1"
#110000
0"
#115000
b1010 !
b1010 '
b1010 (
1"
#120000
0"
#125000
b1011 !
b1011 '
b1011 (
1"
#130000
0"
#135000
b1100 !
b1100 '
b1100 (
1"
#140000
0"
#145000
b1101 !
b1101 '
b1101 (
1"
#150000
0"
#155000
b1110 !
b1110 '
b1110 (
1"
#160000
0"
#165000
b1111 !
b1111 '
b1111 (
1"
#170000
0)
0"
0#
#175000
1"
#180000
0"
#185000
1"
#190000
0"
#195000
1"
#200000
0"
#205000
1"
#210000
0"
#215000
1"
#220000
0"
#225000
1"
#230000
0"
#235000
1"
#240000
0"
#245000
1"
#250000
0"
#255000
1"
#260000
0"
#265000
1"
#270000
0"
#275000
1"
#280000
0"
#285000
1"
#290000
0"
#295000
1"
#300000
0"
#305000
1"
#310000
0"
#315000
1"
#320000
1)
0"
1#
#325000
b10000 !
b10000 '
b10000 (
1"
#330000
0"
#335000
b10001 !
b10001 '
b10001 (
1"
#340000
0"
#345000
b10010 !
b10010 '
b10010 (
1"
#350000
0"
#355000
b10011 !
b10011 '
b10011 (
1"
#360000
0"
#365000
b10100 !
b10100 '
b10100 (
1"
#370000
0"
#375000
b10101 !
b10101 '
b10101 (
1"
#380000
0"
#385000
b10110 !
b10110 '
b10110 (
1"
#390000
0"
#395000
b10111 !
b10111 '
b10111 (
1"
#400000
0"
#405000
b11000 !
b11000 '
b11000 (
1"
#410000
0"
#415000
b11001 !
b11001 '
b11001 (
1"
#420000
0"
#425000
b11010 !
b11010 '
b11010 (
1"
#430000
0"
#435000
b11011 !
b11011 '
b11011 (
1"
#440000
0"
#445000
b11100 !
b11100 '
b11100 (
1"
#450000
0"
#455000
b11101 !
b11101 '
b11101 (
1"
#460000
0"
#465000
b11110 !
b11110 '
b11110 (
1"
#470000
b0 !
b0 '
b0 (
0"
0$
#475000
1"
#480000
0"
1$
#485000
b1 !
b1 '
b1 (
1"
#490000
0"
#495000
b10 !
b10 '
b10 (
1"
#500000
0"
#505000
b11 !
b11 '
b11 (
1"
#510000
0"
#515000
b100 !
b100 '
b100 (
1"
#520000
0"
#525000
b101 !
b101 '
b101 (
1"
#530000
0"
#535000
b110 !
b110 '
b110 (
1"
#540000
0"
#545000
b111 !
b111 '
b111 (
1"
#550000
0"
#555000
b1000 !
b1000 '
b1000 (
1"
#560000
0"
#565000
b1001 !
b1001 '
b1001 (
1"
#570000
0"
#575000
b1010 !
b1010 '
b1010 (
1"
#580000
0"
#585000
b1011 !
b1011 '
b1011 (
1"
#590000
0"
#595000
b1100 !
b1100 '
b1100 (
1"
#600000
0"
#605000
b1101 !
b1101 '
b1101 (
1"
#610000
0"
#615000
b1110 !
b1110 '
b1110 (
1"
#620000
0"
#625000
b1111 !
b1111 '
b1111 (
1"
#630000
0"
#635000
b10000 !
b10000 '
b10000 (
1"
#640000
0)
0"
0#
#645000
1"
#650000
0"
#655000
1"
#660000
0"
#665000
1"
#670000
0"
#675000
1"
#680000
0"
#685000
1"
#690000
0"
#695000
1"
#700000
0"
#705000
1"
#710000
0"
#715000
1"
#720000
0"
#725000
1"
#730000
0"
#735000
1"
#740000
0"
#745000
1"
#750000
0"
#755000
1"
#760000
0"
#765000
1"
#770000
0"
#775000
1"
#780000
0"
#785000
1"
#790000
1)
0"
1#
#795000
b10001 !
b10001 '
b10001 (
1"
#800000
0"
#805000
b10010 !
b10010 '
b10010 (
1"
#810000
0"
#815000
b10011 !
b10011 '
b10011 (
1"
#820000
0"
#825000
b10100 !
b10100 '
b10100 (
1"
#830000
0"
#835000
b10101 !
b10101 '
b10101 (
1"
#840000
0"
#845000
b10110 !
b10110 '
b10110 (
1"
#850000
0"
#855000
b10111 !
b10111 '
b10111 (
1"
#860000
0"
#865000
b11000 !
b11000 '
b11000 (
1"
#870000
0"
#875000
b11001 !
b11001 '
b11001 (
1"
#880000
0"
#885000
b11010 !
b11010 '
b11010 (
1"
#890000
0"
#895000
b11011 !
b11011 '
b11011 (
1"
#900000
0"
#905000
b11100 !
b11100 '
b11100 (
1"
#910000
0"
#915000
b11101 !
b11101 '
b11101 (
1"
#920000
0"
#925000
b11110 !
b11110 '
b11110 (
1"
#930000
0"
#935000
b11111 !
b11111 '
b11111 (
1"
