src/rng_data_path_counter.v
//////////////////////////////////////////////////////////////////////////////////
// Company: 
// Engineer: 
// 
// Create Date:    21:11:06 01/30/2026 
// Design Name: 
// Module Name:    rng_data_path_counter
// Project Name: 
// Target Devices: 
// Tool versions: 
// Description: 
//
// Dependencies: 
//
// Revision: 
// Revision 0.01 - File Created
// Additional Comments: 
//
//////////////////////////////////////////////////////////////////////////////////

module rng_data_path_counter(
    input  wire       clk_i,
    input  wire       rst_i,
    input  wire       req_num_i,
    output wire [7:0] next_num_o
);

reg [7:0] num_counter;
reg       req_num_i_d;
wire      req_rise;

assign req_rise    = req_num_i & ~req_num_i_d;
assign next_num_o  = num_counter;

always @(posedge clk_i or negedge rst_i) begin
    if (!rst_i) begin
        num_counter <= 8'd0;
        req_num_i_d <= 1'b0;
    end else begin
        req_num_i_d <= req_num_i;

        if (req_rise) begin
            if (num_counter == 8'd63)
                num_counter <= 8'd0;
            else
                num_counter <= num_counter + 8'd1;
        end
    end
end

endmodule

testbenchs/testbench_data_path_counter.v
`timescale 1ns / 1ps

////////////////////////////////////////////////////////////////////////////////
// Company: 
// Engineer:
//
// Create Date:   09:35:42 01/31/2026
// Design Name:   seed_random_1_data_path_counter
// Module Name:   /home/matheus/ISE_projects/seed_random_1/tb1.v
// Project Name:  seed_random_1
// Target Device:  
// Tool versions:  
// Description: 
//
// Verilog Test Fixture created by ISE for module: seed_random_1_data_path_counter
//
// Dependencies:
// 
// Revision:
// Revision 0.01 - File Created
// Additional Comments:
// 
////////////////////////////////////////////////////////////////////////////////

module testbench_data_path_counter;

	// Inputs
	reg clk_i;
	reg rst_i;
	reg req_num_i;

	// Outputs
	wire [7:0] next_num_o;

	// Instantiate the Unit Under Test (UUT)
	rng_data_path_counter uut (
		.clk_i(clk_i), 
		.rst_i(rst_i), 
		.req_num_i(req_num_i), 
		.next_num_o(next_num_o)
	);

    initial 
        begin: Clock_generator
          clk_i = 0;
          forever #3 clk_i = ~clk_i;
        end

	task reset;
		rst_i = 0;
		#10;
		rst_i = 1;
		#10;
	endtask 

    initial 
        begin: req
          req_num_i = 0;
          forever #50 req_num_i = ~req_num_i;
        end

	initial 
        begin
            // Initialize Inputs
			reset();
			#5000;
			$finish;
        end
      
    initial 
        begin: Wavedump
            $dumpfile("../waveforms/data_path_counter.vcd");
            $dumpvars(0);
        end

endmodule

waveforms/data_path_counter.vcd
$date
	Sun Feb  8 09:12:52 2026
$end
$version
	Icarus Verilog
$end
$timescale
	1ps
$end
$scope module testbench_data_path_counter $end
$var wire 8 ! next_num_o [7:0] $end
$var reg 1 " clk_i $end
$var reg 1 # req_num_i $end
$var reg 1 $ rst_i $end
$scope module uut $end
$var wire 1 " clk_i $end
$var wire 8 % next_num_o [7:0] $end
$var wire 1 # req_num_i $end
$var wire 1 & req_rise $end
$var wire 1 $ rst_i $end
$var reg 8 ' num_counter [7:0] $end
$var reg 1 ( req_num_i_d $end
$upscope $end
$scope begin Clock_generator $end
$upscope $end
$scope begin Wavedump $end
$upscope $end
$scope begin req $end
$upscope $end
$scope task reset $end
$upscope $end
$upscope $end
$enddefinitions $end
$comment Show the parameter values. $end
$dumpall
$end
#0
$dumpvars
0(
b0 '
0&
b0 %
0$
0#
0"
b0 !
$end
#3000
1"
#6000
0"
#9000
1"
#10000
1$
#12000
0"
#15000
1"
#18000
0"
#21000
1"
#24000
0"
#27000
1"
#30000
0"
#33000
1"
#36000
0"
#39000
1"
#42000
0"
#45000
1"
#48000
0"
#50000
1&
1#
#51000
0&
b1 !
b1 %
b1 '
1(
1"
#54000
0"
#57000
1"
#60000
0"
#63000
1"
#66000
0"
#69000
1"
#72000
0"
#75000
1"
#78000
0"
#81000
1"
#84000
0"
#87000
1"
#90000
0"
#93000
1"
#96000
0"
#99000
1"
#100000
0#
#102000
0"
#105000
0(
1"
#108000
0"
#111000
1"
#114000
0"
#117000
1"
#120000
0"
#123000
1"
#126000
0"
#129000
1"
#132000
0"
#135000
1"
#138000
0"
#141000
1"
#144000
0"
#147000
1"
#150000
1&
0"
1#
#153000
0&
b10 !
b10 %
b10 '
1(
1"
#156000
0"
#159000
1"
#162000
0"
#165000
1"
#168000
0"
#171000
1"
#174000
0"
#177000
1"
#180000
0"
#183000
1"
#186000
0"
#189000
1"
#192000
0"
#195000
1"
#198000
0"
#200000
0#
#201000
0(
1"
#204000
0"
#207000
1"
#210000
0"
#213000
1"
#216000
0"
#219000
1"
#222000
0"
#225000
1"
#228000
0"
#231000
1"
#234000
0"
#237000
1"
#240000
0"
#243000
1"
#246000
0"
#249000
1"
#250000
1&
1#
#252000
0"
#255000
0&
b11 !
b11 %
b11 '
1(
1"
#258000
0"
#261000
1"
#264000
0"
#267000
1"
#270000
0"
#273000
1"
#276000
0"
#279000
1"
#282000
0"
#285000
1"
#288000
0"
#291000
1"
#294000
0"
#297000
1"
#300000
0"
0#
#303000
0(
1"
#306000
0"
#309000
1"
#312000
0"
#315000
1"
#318000
0"
#321000
1"
#324000
0"
#327000
1"
#330000
0"
#333000
1"
#336000
0"
#339000
1"
#342000
0"
#345000
1"
#348000
0"
#350000
1&
1#
#351000
0&
b100 !
b100 %
b100 '
1(
1"
#354000
0"
#357000
1"
#360000
0"
#363000
1"
#366000
0"
#369000
1"
#372000
0"
#375000
1"
#378000
0"
#381000
1"
#384000
0"
#387000
1"
#390000
0"
#393000
1"
#396000
0"
#399000
1"
#400000
0#
#402000
0"
#405000
0(
1"
#408000
0"
#411000
1"
#414000
0"
#417000
1"
#420000
0"
#423000
1"
#426000
0"
#429000
1"
#432000
0"
#435000
1"
#438000
0"
#441000
1"
#444000
0"
#447000
1"
#450000
1&
0"
1#
#453000
0&
b101 !
b101 %
b101 '
1(
1"
#456000
0"
#459000
1"
#462000
0"
#465000
1"
#468000
0"
#471000
1"
#474000
0"
#477000
1"
#480000
0"
#483000
1"
#486000
0"
#489000
1"
#492000
0"
#495000
1"
#498000
0"
#500000
0#
#501000
0(
1"
#504000
0"
#507000
1"
#510000
0"
#513000
1"
#516000
0"
#519000
1"
#522000
0"
#525000
1"
#528000
0"
#531000
1"
#534000
0"
#537000
1"
#540000
0"
#543000
1"
#546000
0"
#549000
1"
#550000
1&
1#
#552000
0"
#555000
0&
b110 !
b110 %
b110 '
1(
1"
#558000
0"
#561000
1"
#564000
0"
#567000
1"
#570000
0"
#573000
1"
#576000
0"
#579000
1"
#582000
0"
#585000
1"
#588000
0"
#591000
1"
#594000
0"
#597000
1"
#600000
0"
0#
#603000
0(
1"
#606000
0"
#609000
1"
#612000
0"
#615000
1"
#618000
0"
#621000
1"
#624000
0"
#627000
1"
#630000
0"
#633000
1"
#636000
0"
#639000
1"
#642000
0"
#645000
1"
#648000
0"
#650000
1&
1#
#651000
0&
b111 !
b111 %
b111 '
1(
1"
#654000
0"
#657000
1"
#660000
0"
#663000
1"
#666000
0"
#669000
1"
#672000
0"
#675000
1"
#678000
0"
#681000
1"
#684000
0"
#687000
1"
#690000
0"
#693000
1"
#696000
0"
#699000
1"
#700000
0#
#702000
0"
#705000
0(
1"
#708000
0"
#711000
1"
#714000
0"
#717000
1"
#720000
0"
#723000
1"
#726000
0"
#729000
1"
#732000
0"
#735000
1"
#738000
0"
#741000
1"
#744000
0"
#747000
1"
#750000
1&
0"
1#
#753000
0&
b1000 !
b1000 %
b1000 '
1(
1"
#756000
0"
#759000
1"
#762000
0"
#765000
1"
#768000
0"
#771000
1"
#774000
0"
#777000
1"
#780000
0"
#783000
1"
#786000
0"
#789000
1"
#792000
0"
#795000
1"
#798000
0"
#800000
0#
#801000
0(
1"
#804000
0"
#807000
1"
#810000
0"
#813000
1"
#816000
0"
#819000
1"
#822000
0"
#825000
1"
#828000
0"
#831000
1"
#834000
0"
#837000
1"
#840000
0"
#843000
1"
#846000
0"
#849000
1"
#850000
1&
1#
#852000
0"
#855000
0&
b1001 !
b1001 %
b1001 '
1(
1"
#858000
0"
#861000
1"
#864000
0"
#867000
1"
#870000
0"
#873000
1"
#876000
0"
#879000
1"
#882000
0"
#885000
1"
#888000
0"
#891000
1"
#894000
0"
#897000
1"
#900000
0"
0#
#903000
0(
1"
#906000
0"
#909000
1"
#912000
0"
#915000
1"
#918000
0"
#921000
1"
#924000
0"
#927000
1"
#930000
0"
#933000
1"
#936000
0"
#939000
1"
#942000
0"
#945000
1"
#948000
0"
#950000
1&
1#
#951000
0&
b1010 !
b1010 %
b1010 '
1(
1"
#954000
0"
#957000
1"
#960000
0"
#963000
1"
#966000
0"
#969000
1"
#972000
0"
#975000
1"
#978000
0"
#981000
1"
#984000
0"
#987000
1"
#990000
0"
#993000
1"
#996000
0"
#999000
1"
#1000000
0#
#1002000
0"
#1005000
0(
1"
#1008000
0"
#1011000
1"
#1014000
0"
#1017000
1"
#1020000
0"
#1023000
1"
#1026000
0"
#1029000
1"
#1032000
0"
#1035000
1"
#1038000
0"
#1041000
1"
#1044000
0"
#1047000
1"
#1050000
1&
0"
1#
#1053000
0&
b1011 !
b1011 %
b1011 '
1(
1"
#1056000
0"
#1059000
1"
#1062000
0"
#1065000
1"
#1068000
0"
#1071000
1"
#1074000
0"
#1077000
1"
#1080000
0"
#1083000
1"
#1086000
0"
#1089000
1"
#1092000
0"
#1095000
1"
#1098000
0"
#1100000
0#
#1101000
0(
1"
#1104000
0"
#1107000
1"
#1110000
0"
#1113000
1"
#1116000
0"
#1119000
1"
#1122000
0"
#1125000
1"
#1128000
0"
#1131000
1"
#1134000
0"
#1137000
1"
#1140000
0"
#1143000
1"
#1146000
0"
#1149000
1"
#1150000
1&
1#
#1152000
0"
#1155000
0&
b1100 !
b1100 %
b1100 '
1(
1"
#1158000
0"
#1161000
1"
#1164000
0"
#1167000
1"
#1170000
0"
#1173000
1"
#1176000
0"
#1179000
1"
#1182000
0"
#1185000
1"
#1188000
0"
#1191000
1"
#1194000
0"
#1197000
1"
#1200000
0"
0#
#1203000
0(
1"
#1206000
0"
#1209000
1"
#1212000
0"
#1215000
1"
#1218000
0"
#1221000
1"
#1224000
0"
#1227000
1"
#1230000
0"
#1233000
1"
#1236000
0"
#1239000
1"
#1242000
0"
#1245000
1"
#1248000
0"
#1250000
1&
1#
#1251000
0&
b1101 !
b1101 %
b1101 '
1(
1"
#1254000
0"
#1257000
1"
#1260000
0"
#1263000
1"
#1266000
0"
#1269000
1"
#1272000
0"
#1275000
1"
#1278000
0"
#1281000
1"
#1284000
0"
#1287000
1"
#1290000
0"
#1293000
1"
#1296000
0"
#1299000
1"
#1300000
0#
#1302000
0"
#1305000
0(
1"
#1308000
0"
#1311000
1"
#1314000
0"
#1317000
1"
#1320000
0"
#1323000
1"
#1326000
0"
#1329000
1"
#1332000
0"
#1335000
1"
#1338000
0"
#1341000
1"
#1344000
0"
#1347000
1"
#1350000
1&
0"
1#
#1353000
0&
b1110 !
b1110 %
b1110 '
1(
1"
#1356000
0"
#1359000
1"
#1362000
0"
#1365000
1"
#1368000
0"
#1371000
1"
#1374000
0"
#1377000
1"
#1380000
0"
#1383000
1"
#1386000
0"
#1389000
1"
#1392000
0"
#1395000
1"
#1398000
0"
#1400000
0#
#1401000
0(
1"
#1404000
0"
#1407000
1"
#1410000
0"
#1413000
1"
#1416000
0"
#1419000
1"
#1422000
0"
#1425000
1"
#1428000
0"
#1431000
1"
#1434000
0"
#1437000
1"
#1440000
0"
#1443000
1"
#1446000
0"
#1449000
1"
#1450000
1&
1#
#1452000
0"
#1455000
0&
b1111 !
b1111 %
b1111 '
1(
1"
#1458000
0"
#1461000
1"
#1464000
0"
#1467000
1"
#1470000
0"
#1473000
1"
#1476000
0"
#1479000
1"
#1482000
0"
#1485000
1"
#1488000
0"
#1491000
1"
#1494000
0"
#1497000
1"
#1500000
0"
0#
#1503000
0(
1"
#1506000
0"
#1509000
1"
#1512000
0"
#1515000
1"
#1518000
0"
#1521000
1"
#1524000
0"
#1527000
1"
#1530000
0"
#1533000
1"
#1536000
0"
#1539000
1"
#1542000
0"
#1545000
1"
#1548000
0"
#1550000
1&
1#
#1551000
0&
b10000 !
b10000 %
b10000 '
1(
1"
#1554000
0"
#1557000
1"
#1560000
0"
#1563000
1"
#1566000
0"
#1569000
1"
#1572000
0"
#1575000
1"
#1578000
0"
#1581000
1"
#1584000
0"
#1587000
1"
#1590000
0"
#1593000
1"
#1596000
0"
#1599000
1"
#1600000
0#
#1602000
0"
#1605000
0(
1"
#1608000
0"
#1611000
1"
#1614000
0"
#1617000
1"
#1620000
0"
#1623000
1"
#1626000
0"
#1629000
1"
#1632000
0"
#1635000
1"
#1638000
0"
#1641000
1"
#1644000
0"
#1647000
1"
#1650000
1&
0"
1#
#1653000
0&
b10001 !
b10001 %
b10001 '
1(
1"
#1656000
0"
#1659000
1"
#1662000
0"
#1665000
1"
#1668000
0"
#1671000
1"
#1674000
0"
#1677000
1"
#1680000
0"
#1683000
1"
#1686000
0"
#1689000
1"
#1692000
0"
#1695000
1"
#1698000
0"
#1700000
0#
#1701000
0(
1"
#1704000
0"
#1707000
1"
#1710000
0"
#1713000
1"
#1716000
0"
#1719000
1"
#1722000
0"
#1725000
1"
#1728000
0"
#1731000
1"
#1734000
0"
#1737000
1"
#1740000
0"
#1743000
1"
#1746000
0"
#1749000
1"
#1750000
1&
1#
#1752000
0"
#1755000
0&
b10010 !
b10010 %
b10010 '
1(
1"
#1758000
0"
#1761000
1"
#1764000
0"
#1767000
1"
#1770000
0"
#1773000
1"
#1776000
0"
#1779000
1"
#1782000
0"
#1785000
1"
#1788000
0"
#1791000
1"
#1794000
0"
#1797000
1"
#1800000
0"
0#
#1803000
0(
1"
#1806000
0"
#1809000
1"
#1812000
0"
#1815000
1"
#1818000
0"
#1821000
1"
#1824000
0"
#1827000
1"
#1830000
0"
#1833000
1"
#1836000
0"
#1839000
1"
#1842000
0"
#1845000
1"
#1848000
0"
#1850000
1&
1#
#1851000
0&
b10011 !
b10011 %
b10011 '
1(
1"
#1854000
0"
#1857000
1"
#1860000
0"
#1863000
1"
#1866000
0"
#1869000
1"
#1872000
0"
#1875000
1"
#1878000
0"
#1881000
1"
#1884000
0"
#1887000
1"
#1890000
0"
#1893000
1"
#1896000
0"
#1899000
1"
#1900000
0#
#1902000
0"
#1905000
0(
1"
#1908000
0"
#1911000
1"
#1914000
0"
#1917000
1"
#1920000
0"
#1923000
1"
#1926000
0"
#1929000
1"
#1932000
0"
#1935000
1"
#1938000
0"
#1941000
1"
#1944000
0"
#1947000
1"
#1950000
1&
0"
1#
#1953000
0&
b10100 !
b10100 %
b10100 '
1(
1"
#1956000
0"
#1959000
1"
#1962000
0"
#1965000
1"
#1968000
0"
#1971000
1"
#1974000
0"
#1977000
1"
#1980000
0"
#1983000
1"
#1986000
0"
#1989000
1"
#1992000
0"
#1995000
1"
#1998000
0"
#2000000
0#
#2001000
0(
1"
#2004000
0"
#2007000
1"
#2010000
0"
#2013000
1"
#2016000
0"
#2019000
1"
#2022000
0"
#2025000
1"
#2028000
0"
#2031000
1"
#2034000
0"
#2037000
1"
#2040000
0"
#2043000
1"
#2046000
0"
#2049000
1"
#2050000
1&
1#
#2052000
0"
#2055000
0&
b10101 !
b10101 %
b10101 '
1(
1"
#2058000
0"
#2061000
1"
#2064000
0"
#2067000
1"
#2070000
0"
#2073000
1"
#2076000
0"
#2079000
1"
#2082000
0"
#2085000
1"
#2088000
0"
#2091000
1"
#2094000
0"
#2097000
1"
#2100000
0"
0#
#2103000
0(
1"
#2106000
0"
#2109000
1"
#2112000
0"
#2115000
1"
#2118000
0"
#2121000
1"
#2124000
0"
#2127000
1"
#2130000
0"
#2133000
1"
#2136000
0"
#2139000
1"
#2142000
0"
#2145000
1"
#2148000
0"
#2150000
1&
1#
#2151000
0&
b10110 !
b10110 %
b10110 '
1(
1"
#2154000
0"
#2157000
1"
#2160000
0"
#2163000
1"
#2166000
0"
#2169000
1"
#2172000
0"
#2175000
1"
#2178000
0"
#2181000
1"
#2184000
0"
#2187000
1"
#2190000
0"
#2193000
1"
#2196000
0"
#2199000
1"
#2200000
0#
#2202000
0"
#2205000
0(
1"
#2208000
0"
#2211000
1"
#2214000
0"
#2217000
1"
#2220000
0"
#2223000
1"
#2226000
0"
#2229000
1"
#2232000
0"
#2235000
1"
#2238000
0"
#2241000
1"
#2244000
0"
#2247000
1"
#2250000
1&
0"
1#
#2253000
0&
b10111 !
b10111 %
b10111 '
1(
1"
#2256000
0"
#2259000
1"
#2262000
0"
#2265000
1"
#2268000
0"
#2271000
1"
#2274000
0"
#2277000
1"
#2280000
0"
#2283000
1"
#2286000
0"
#2289000
1"
#2292000
0"
#2295000
1"
#2298000
0"
#2300000
0#
#2301000
0(
1"
#2304000
0"
#2307000
1"
#2310000
0"
#2313000
1"
#2316000
0"
#2319000
1"
#2322000
0"
#2325000
1"
#2328000
0"
#2331000
1"
#2334000
0"
#2337000
1"
#2340000
0"
#2343000
1"
#2346000
0"
#2349000
1"
#2350000
1&
1#
#2352000
0"
#2355000
0&
b11000 !
b11000 %
b11000 '
1(
1"
#2358000
0"
#2361000
1"
#2364000
0"
#2367000
1"
#2370000
0"
#2373000
1"
#2376000
0"
#2379000
1"
#2382000
0"
#2385000
1"
#2388000
0"
#2391000
1"
#2394000
0"
#2397000
1"
#2400000
0"
0#
#2403000
0(
1"
#2406000
0"
#2409000
1"
#2412000
0"
#2415000
1"
#2418000
0"
#2421000
1"
#2424000
0"
#2427000
1"
#2430000
0"
#2433000
1"
#2436000
0"
#2439000
1"
#2442000
0"
#2445000
1"
#2448000
0"
#2450000
1&
1#
#2451000
0&
b11001 !
b11001 %
b11001 '
1(
1"
#2454000
0"
#2457000
1"
#2460000
0"
#2463000
1"
#2466000
0"
#2469000
1"
#2472000
0"
#2475000
1"
#2478000
0"
#2481000
1"
#2484000
0"
#2487000
1"
#2490000
0"
#2493000
1"
#2496000
0"
#2499000
1"
#2500000
0#
#2502000
0"
#2505000
0(
1"
#2508000
0"
#2511000
1"
#2514000
0"
#2517000
1"
#2520000
0"
#2523000
1"
#2526000
0"
#2529000
1"
#2532000
0"
#2535000
1"
#2538000
0"
#2541000
1"
#2544000
0"
#2547000
1"
#2550000
1&
0"
1#
#2553000
0&
b11010 !
b11010 %
b11010 '
1(
1"
#2556000
0"
#2559000
1"
#2562000
0"
#2565000
1"
#2568000
0"
#2571000
1"
#2574000
0"
#2577000
1"
#2580000
0"
#2583000
1"
#2586000
0"
#2589000
1"
#2592000
0"
#2595000
1"
#2598000
0"
#2600000
0#
#2601000
0(
1"
#2604000
0"
#2607000
1"
#2610000
0"
#2613000
1"
#2616000
0"
#2619000
1"
#2622000
0"
#2625000
1"
#2628000
0"
#2631000
1"
#2634000
0"
#2637000
1"
#2640000
0"
#2643000
1"
#2646000
0"
#2649000
1"
#2650000
1&
1#
#2652000
0"
#2655000
0&
b11011 !
b11011 %
b11011 '
1(
1"
#2658000
0"
#2661000
1"
#2664000
0"
#2667000
1"
#2670000
0"
#2673000
1"
#2676000
0"
#2679000
1"
#2682000
0"
#2685000
1"
#2688000
0"
#2691000
1"
#2694000
0"
#2697000
1"
#2700000
0"
0#
#2703000
0(
1"
#2706000
0"
#2709000
1"
#2712000
0"
#2715000
1"
#2718000
0"
#2721000
1"
#2724000
0"
#2727000
1"
#2730000
0"
#2733000
1"
#2736000
0"
#2739000
1"
#2742000
0"
#2745000
1"
#2748000
0"
#2750000
1&
1#
#2751000
0&
b11100 !
b11100 %
b11100 '
1(
1"
#2754000
0"
#2757000
1"
#2760000
0"
#2763000
1"
#2766000
0"
#2769000
1"
#2772000
0"
#2775000
1"
#2778000
0"
#2781000
1"
#2784000
0"
#2787000
1"
#2790000
0"
#2793000
1"
#2796000
0"
#2799000
1"
#2800000
0#
#2802000
0"
#2805000
0(
1"
#2808000
0"
#2811000
1"
#2814000
0"
#2817000
1"
#2820000
0"
#2823000
1"
#2826000
0"
#2829000
1"
#2832000
0"
#2835000
1"
#2838000
0"
#2841000
1"
#2844000
0"
#2847000
1"
#2850000
1&
0"
1#
#2853000
0&
b11101 !
b11101 %
b11101 '
1(
1"
#2856000
0"
#2859000
1"
#2862000
0"
#2865000
1"
#2868000
0"
#2871000
1"
#2874000
0"
#2877000
1"
#2880000
0"
#2883000
1"
#2886000
0"
#2889000
1"
#2892000
0"
#2895000
1"
#2898000
0"
#2900000
0#
#2901000
0(
1"
#2904000
0"
#2907000
1"
#2910000
0"
#2913000
1"
#2916000
0"
#2919000
1"
#2922000
0"
#2925000
1"
#2928000
0"
#2931000
1"
#2934000
0"
#2937000
1"
#2940000
0"
#2943000
1"
#2946000
0"
#2949000
1"
#2950000
1&
1#
#2952000
0"
#2955000
0&
b11110 !
b11110 %
b11110 '
1(
1"
#2958000
0"
#2961000
1"
#2964000
0"
#2967000
1"
#2970000
0"
#2973000
1"
#2976000
0"
#2979000
1"
#2982000
0"
#2985000
1"
#2988000
0"
#2991000
1"
#2994000
0"
#2997000
1"
#3000000
0"
0#
#3003000
0(
1"
#3006000
0"
#3009000
1"
#3012000
0"
#3015000
1"
#3018000
0"
#3021000
1"
#3024000
0"
#3027000
1"
#3030000
0"
#3033000
1"
#3036000
0"
#3039000
1"
#3042000
0"
#3045000
1"
#3048000
0"
#3050000
1&
1#
#3051000
0&
b11111 !
b11111 %
b11111 '
1(
1"
#3054000
0"
#3057000
1"
#3060000
0"
#3063000
1"
#3066000
0"
#3069000
1"
#3072000
0"
#3075000
1"
#3078000
0"
#3081000
1"
#3084000
0"
#3087000
1"
#3090000
0"
#3093000
1"
#3096000
0"
#3099000
1"
#3100000
0#
#3102000
0"
#3105000
0(
1"
#3108000
0"
#3111000
1"
#3114000
0"
#3117000
1"
#3120000
0"
#3123000
1"
#3126000
0"
#3129000
1"
#3132000
0"
#3135000
1"
#3138000
0"
#3141000
1"
#3144000
0"
#3147000
1"
#3150000
1&
0"
1#
#3153000
0&
b100000 !
b100000 %
b100000 '
1(
1"
#3156000
0"
#3159000
1"
#3162000
0"
#3165000
1"
#3168000
0"
#3171000
1"
#3174000
0"
#3177000
1"
#3180000
0"
#3183000
1"
#3186000
0"
#3189000
1"
#3192000
0"
#3195000
1"
#3198000
0"
#3200000
0#
#3201000
0(
1"
#3204000
0"
#3207000
1"
#3210000
0"
#3213000
1"
#3216000
0"
#3219000
1"
#3222000
0"
#3225000
1"
#3228000
0"
#3231000
1"
#3234000
0"
#3237000
1"
#3240000
0"
#3243000
1"
#3246000
0"
#3249000
1"
#3250000
1&
1#
#3252000
0"
#3255000
0&
b100001 !
b100001 %
b100001 '
1(
1"
#3258000
0"
#3261000
1"
#3264000
0"
#3267000
1"
#3270000
0"
#3273000
1"
#3276000
0"
#3279000
1"
#3282000
0"
#3285000
1"
#3288000
0"
#3291000
1"
#3294000
0"
#3297000
1"
#3300000
0"
0#
#3303000
0(
1"
#3306000
0"
#3309000
1"
#3312000
0"
#3315000
1"
#3318000
0"
#3321000
1"
#3324000
0"
#3327000
1"
#3330000
0"
#3333000
1"
#3336000
0"
#3339000
1"
#3342000
0"
#3345000
1"
#3348000
0"
#3350000
1&
1#
#3351000
0&
b100010 !
b100010 %
b100010 '
1(
1"
#3354000
0"
#3357000
1"
#3360000
0"
#3363000
1"
#3366000
0"
#3369000
1"
#3372000
0"
#3375000
1"
#3378000
0"
#3381000
1"
#3384000
0"
#3387000
1"
#3390000
0"
#3393000
1"
#3396000
0"
#3399000
1"
#3400000
0#
#3402000
0"
#3405000
0(
1"
#3408000
0"
#3411000
1"
#3414000
0"
#3417000
1"
#3420000
0"
#3423000
1"
#3426000
0"
#3429000
1"
#3432000
0"
#3435000
1"
#3438000
0"
#3441000
1"
#3444000
0"
#3447000
1"
#3450000
1&
0"
1#
#3453000
0&
b100011 !
b100011 %
b100011 '
1(
1"
#3456000
0"
#3459000
1"
#3462000
0"
#3465000
1"
#3468000
0"
#3471000
1"
#3474000
0"
#3477000
1"
#3480000
0"
#3483000
1"
#3486000
0"
#3489000
1"
#3492000
0"
#3495000
1"
#3498000
0"
#3500000
0#
#3501000
0(
1"
#3504000
0"
#3507000
1"
#3510000
0"
#3513000
1"
#3516000
0"
#3519000
1"
#3522000
0"
#3525000
1"
#3528000
0"
#3531000
1"
#3534000
0"
#3537000
1"
#3540000
0"
#3543000
1"
#3546000
0"
#3549000
1"
#3550000
1&
1#
#3552000
0"
#3555000
0&
b100100 !
b100100 %
b100100 '
1(
1"
#3558000
0"
#3561000
1"
#3564000
0"
#3567000
1"
#3570000
0"
#3573000
1"
#3576000
0"
#3579000
1"
#3582000
0"
#3585000
1"
#3588000
0"
#3591000
1"
#3594000
0"
#3597000
1"
#3600000
0"
0#
#3603000
0(
1"
#3606000
0"
#3609000
1"
#3612000
0"
#3615000
1"
#3618000
0"
#3621000
1"
#3624000
0"
#3627000
1"
#3630000
0"
#3633000
1"
#3636000
0"
#3639000
1"
#3642000
0"
#3645000
1"
#3648000
0"
#3650000
1&
1#
#3651000
0&
b100101 !
b100101 %
b100101 '
1(
1"
#3654000
0"
#3657000
1"
#3660000
0"
#3663000
1"
#3666000
0"
#3669000
1"
#3672000
0"
#3675000
1"
#3678000
0"
#3681000
1"
#3684000
0"
#3687000
1"
#3690000
0"
#3693000
1"
#3696000
0"
#3699000
1"
#3700000
0#
#3702000
0"
#3705000
0(
1"
#3708000
0"
#3711000
1"
#3714000
0"
#3717000
1"
#3720000
0"
#3723000
1"
#3726000
0"
#3729000
1"
#3732000
0"
#3735000
1"
#3738000
0"
#3741000
1"
#3744000
0"
#3747000
1"
#3750000
1&
0"
1#
#3753000
0&
b100110 !
b100110 %
b100110 '
1(
1"
#3756000
0"
#3759000
1"
#3762000
0"
#3765000
1"
#3768000
0"
#3771000
1"
#3774000
0"
#3777000
1"
#3780000
0"
#3783000
1"
#3786000
0"
#3789000
1"
#3792000
0"
#3795000
1"
#3798000
0"
#3800000
0#
#3801000
0(
1"
#3804000
0"
#3807000
1"
#3810000
0"
#3813000
1"
#3816000
0"
#3819000
1"
#3822000
0"
#3825000
1"
#3828000
0"
#3831000
1"
#3834000
0"
#3837000
1"
#3840000
0"
#3843000
1"
#3846000
0"
#3849000
1"
#3850000
1&
1#
#3852000
0"
#3855000
0&
b100111 !
b100111 %
b100111 '
1(
1"
#3858000
0"
#3861000
1"
#3864000
0"
#3867000
1"
#3870000
0"
#3873000
1"
#3876000
0"
#3879000
1"
#3882000
0"
#3885000
1"
#3888000
0"
#3891000
1"
#3894000
0"
#3897000
1"
#3900000
0"
0#
#3903000
0(
1"
#3906000
0"
#3909000
1"
#3912000
0"
#3915000
1"
#3918000
0"
#3921000
1"
#3924000
0"
#3927000
1"
#3930000
0"
#3933000
1"
#3936000
0"
#3939000
1"
#3942000
0"
#3945000
1"
#3948000
0"
#3950000
1&
1#
#3951000
0&
b101000 !
b101000 %
b101000 '
1(
1"
#3954000
0"
#3957000
1"
#3960000
0"
#3963000
1"
#3966000
0"
#3969000
1"
#3972000
0"
#3975000
1"
#3978000
0"
#3981000
1"
#3984000
0"
#3987000
1"
#3990000
0"
#3993000
1"
#3996000
0"
#3999000
1"
#4000000
0#
#4002000
0"
#4005000
0(
1"
#4008000
0"
#4011000
1"
#4014000
0"
#4017000
1"
#4020000
0"
#4023000
1"
#4026000
0"
#4029000
1"
#4032000
0"
#4035000
1"
#4038000
0"
#4041000
1"
#4044000
0"
#4047000
1"
#4050000
1&
0"
1#
#4053000
0&
b101001 !
b101001 %
b101001 '
1(
1"
#4056000
0"
#4059000
1"
#4062000
0"
#4065000
1"
#4068000
0"
#4071000
1"
#4074000
0"
#4077000
1"
#4080000
0"
#4083000
1"
#4086000
0"
#4089000
1"
#4092000
0"
#4095000
1"
#4098000
0"
#4100000
0#
#4101000
0(
1"
#4104000
0"
#4107000
1"
#4110000
0"
#4113000
1"
#4116000
0"
#4119000
1"
#4122000
0"
#4125000
1"
#4128000
0"
#4131000
1"
#4134000
0"
#4137000
1"
#4140000
0"
#4143000
1"
#4146000
0"
#4149000
1"
#4150000
1&
1#
#4152000
0"
#4155000
0&
b101010 !
b101010 %
b101010 '
1(
1"
#4158000
0"
#4161000
1"
#4164000
0"
#4167000
1"
#4170000
0"
#4173000
1"
#4176000
0"
#4179000
1"
#4182000
0"
#4185000
1"
#4188000
0"
#4191000
1"
#4194000
0"
#4197000
1"
#4200000
0"
0#
#4203000
0(
1"
#4206000
0"
#4209000
1"
#4212000
0"
#4215000
1"
#4218000
0"
#4221000
1"
#4224000
0"
#4227000
1"
#4230000
0"
#4233000
1"
#4236000
0"
#4239000
1"
#4242000
0"
#4245000
1"
#4248000
0"
#4250000
1&
1#
#4251000
0&
b101011 !
b101011 %
b101011 '
1(
1"
#4254000
0"
#4257000
1"
#4260000
0"
#4263000
1"
#4266000
0"
#4269000
1"
#4272000
0"
#4275000
1"
#4278000
0"
#4281000
1"
#4284000
0"
#4287000
1"
#4290000
0"
#4293000
1"
#4296000
0"
#4299000
1"
#4300000
0#
#4302000
0"
#4305000
0(
1"
#4308000
0"
#4311000
1"
#4314000
0"
#4317000
1"
#4320000
0"
#4323000
1"
#4326000
0"
#4329000
1"
#4332000
0"
#4335000
1"
#4338000
0"
#4341000
1"
#4344000
0"
#4347000
1"
#4350000
1&
0"
1#
#4353000
0&
b101100 !
b101100 %
b101100 '
1(
1"
#4356000
0"
#4359000
1"
#4362000
0"
#4365000
1"
#4368000
0"
#4371000
1"
#4374000
0"
#4377000
1"
#4380000
0"
#4383000
1"
#4386000
0"
#4389000
1"
#4392000
0"
#4395000
1"
#4398000
0"
#4400000
0#
#4401000
0(
1"
#4404000
0"
#4407000
1"
#4410000
0"
#4413000
1"
#4416000
0"
#4419000
1"
#4422000
0"
#4425000
1"
#4428000
0"
#4431000
1"
#4434000
0"
#4437000
1"
#4440000
0"
