src/rng_fifo.v
//////////////////////////////////////////////////////////////////////////////////
// Company: 
// Engineer: 
// 
// Create Date:    21:46:48 01/27/2026 
// Design Name: 
// Module Name:    rng_fifo 
// Project Name: 
// Target Devices: 
// Tool versions: 
// Description: 
//
// Dependencies: 
//
// Revision: 
// Revision 0.01 - File Created
// Additional Comments: 
//
//////////////////////////////////////////////////////////////////////////////////

module rng_fifo #(
    parameter DEPTH         = 72,                       //Profundidade
    parameter T_DEPTH       = (DEPTH-1),                //Profundidade real
    parameter WIDTH         = 8,                        //Largura
    parameter T_WIDTH       = (WIDTH-1),                //Largura "real" para uso vetorial
    parameter SEED_TOT_NUMB = 64,                       //Total de números das seeds agrupados
    parameter COUNT_WIDTH   = $clog2(SEED_TOT_NUMB),    //Largura do contador de ciclos
    parameter T_COUNT_WID   = (COUNT_WIDTH-1)           //Largura "real" para uso vetorial
    )(
    input clk_i,
    input write,
    input rst_i,
    input [T_WIDTH:0] data_in,

    //data_out:
    output reg [T_WIDTH:0] data_out_00,
    output reg [T_WIDTH:0] data_out_01,
    output reg [T_WIDTH:0] data_out_02,
    output reg [T_WIDTH:0] data_out_03,
    output reg [T_WIDTH:0] data_out_04,
    output reg [T_WIDTH:0] data_out_05,
    output reg [T_WIDTH:0] data_out_06,
    output reg [T_WIDTH:0] data_out_07,
    output reg [T_WIDTH:0] data_out_08,
    output reg [T_WIDTH:0] data_out_09,
    output reg [T_WIDTH:0] data_out_10,
    output reg [T_WIDTH:0] data_out_11,
    output reg [T_WIDTH:0] data_out_12,
    output reg [T_WIDTH:0] data_out_13,
    output reg [T_WIDTH:0] data_out_14,
    output reg [T_WIDTH:0] data_out_15,
    output reg [T_WIDTH:0] data_out_16,
    output reg [T_WIDTH:0] data_out_17,
    output reg [T_WIDTH:0] data_out_18,
    output reg [T_WIDTH:0] data_out_19,
    output reg [T_WIDTH:0] data_out_20,
    output reg [T_WIDTH:0] data_out_21,
    output reg [T_WIDTH:0] data_out_22,
    output reg [T_WIDTH:0] data_out_23,
    output reg [T_WIDTH:0] data_out_24,
    output reg [T_WIDTH:0] data_out_25,
    output reg [T_WIDTH:0] data_out_26,
    output reg [T_WIDTH:0] data_out_27,
    output reg [T_WIDTH:0] data_out_28,
    output reg [T_WIDTH:0] data_out_29,
    output reg [T_WIDTH:0] data_out_30,
    output reg [T_WIDTH:0] data_out_31,
    output reg [T_WIDTH:0] data_out_32,
    output reg [T_WIDTH:0] data_out_33,
    output reg [T_WIDTH:0] data_out_34,
    output reg [T_WIDTH:0] data_out_35,
    output reg [T_WIDTH:0] data_out_36,
    output reg [T_WIDTH:0] data_out_37,
    output reg [T_WIDTH:0] data_out_38,
    output reg [T_WIDTH:0] data_out_39,
    output reg [T_WIDTH:0] data_out_40,
    output reg [T_WIDTH:0] data_out_41,
    output reg [T_WIDTH:0] data_out_42,
    output reg [T_WIDTH:0] data_out_43,
    output reg [T_WIDTH:0] data_out_44,
    output reg [T_WIDTH:0] data_out_45,
    output reg [T_WIDTH:0] data_out_46,
    output reg [T_WIDTH:0] data_out_47,
    output reg [T_WIDTH:0] data_out_48,
    output reg [T_WIDTH:0] data_out_49,
    output reg [T_WIDTH:0] data_out_50,
    output reg [T_WIDTH:0] data_out_51,
    output reg [T_WIDTH:0] data_out_52,
    output reg [T_WIDTH:0] data_out_53,
    output reg [T_WIDTH:0] data_out_54,
    output reg [T_WIDTH:0] data_out_55,
    output reg [T_WIDTH:0] data_out_56,
    output reg [T_WIDTH:0] data_out_57,
    output reg [T_WIDTH:0] data_out_58,
    output reg [T_WIDTH:0] data_out_59,
    output reg [T_WIDTH:0] data_out_60,
    output reg [T_WIDTH:0] data_out_61,
    output reg [T_WIDTH:0] data_out_62,
    output reg [T_WIDTH:0] data_out_63

);
localparam write_data = 1;
localparam await = 0;

reg next_state;

//data_pack:
reg [T_WIDTH:0] data_stack [0:T_DEPTH];

//Contador indo de 0 a 63
reg [T_COUNT_WID:0] cycle_count;

//Variáveis temporárias criada para gerar efeito de detecção de borda
reg  write_d;
wire write_pulse;

//Isso permite o posedge detection em um if:
assign write_pulse = write & ~write_d;

//Variável de sustentação do looping
integer i;

//Control Path:
always @(posedge clk_i or negedge rst_i)
begin
    if (!rst_i)
    begin
        write_d     <= 1'b0; 
        cycle_count <= 6'b000000;
        for (i = 0; i < SEED_TOT_NUMB; i = i + 1)
        begin
            data_stack[i] <= 8'b0;
        end

        data_out_00 <= 8'b0;
        data_out_01 <= 8'b0;
        data_out_02 <= 8'b0;
        data_out_03 <= 8'b0;
        data_out_04 <= 8'b0;
        data_out_05 <= 8'b0;
        data_out_06 <= 8'b0;
        data_out_07 <= 8'b0;
        data_out_08 <= 8'b0;
        data_out_09 <= 8'b0;
        data_out_10 <= 8'b0;
        data_out_11 <= 8'b0;
        data_out_12 <= 8'b0;
        data_out_13 <= 8'b0;
        data_out_14 <= 8'b0;
        data_out_15 <= 8'b0;
        data_out_16 <= 8'b0;
        data_out_17 <= 8'b0;
        data_out_18 <= 8'b0;
        data_out_19 <= 8'b0;
        data_out_20 <= 8'b0;
        data_out_21 <= 8'b0;
        data_out_22 <= 8'b0;
        data_out_23 <= 8'b0;
        data_out_24 <= 8'b0;
        data_out_25 <= 8'b0;
        data_out_26 <= 8'b0;
        data_out_27 <= 8'b0;
        data_out_28 <= 8'b0;
        data_out_29 <= 8'b0;
        data_out_30 <= 8'b0;
        data_out_31 <= 8'b0;
        data_out_32 <= 8'b0;
        data_out_33 <= 8'b0;
        data_out_34 <= 8'b0;
        data_out_35 <= 8'b0;
        data_out_36 <= 8'b0;
        data_out_37 <= 8'b0;
        data_out_38 <= 8'b0;
        data_out_39 <= 8'b0;
        data_out_40 <= 8'b0;
        data_out_41 <= 8'b0;
        data_out_42 <= 8'b0;
        data_out_43 <= 8'b0;
        data_out_44 <= 8'b0;
        data_out_45 <= 8'b0;
        data_out_46 <= 8'b0;
        data_out_47 <= 8'b0;
        data_out_48 <= 8'b0;
        data_out_49 <= 8'b0;
        data_out_50 <= 8'b0;
        data_out_51 <= 8'b0;
        data_out_52 <= 8'b0;
        data_out_53 <= 8'b0;
        data_out_54 <= 8'b0;
        data_out_55 <= 8'b0;
        data_out_56 <= 8'b0;
        data_out_57 <= 8'b0;
        data_out_58 <= 8'b0;
        data_out_59 <= 8'b0;
        data_out_60 <= 8'b0;
        data_out_61 <= 8'b0;
        data_out_62 <= 8'b0;
        data_out_63 <= 8'b0;
    end
    else
    begin
        write_d <= write; 
        if (write_pulse)
        begin
            next_state <= write_data;
        end
        else
        begin
            next_state <= await;
        end
    end
end

//Data-path:
always @(posedge clk_i)
begin
    if (write_pulse === 1'b1)
        begin

            cycle_count   <= cycle_count + 1'b1;
            data_stack[0] <= data_in;

            for (i = (SEED_TOT_NUMB-1); i > 0; i = i - 1)
            begin
                data_stack[i] <= data_stack[i-1];
            end

            data_out_00 <= data_in;
            data_out_01 <= data_stack[0];
            data_out_02 <= data_stack[1];
            data_out_03 <= data_stack[2];
            data_out_04 <= data_stack[3];
            data_out_05 <= data_stack[4];
            data_out_06 <= data_stack[5];
            data_out_07 <= data_stack[6];
            data_out_08 <= data_stack[7];
            data_out_09 <= data_stack[8];
            data_out_10 <= data_stack[9];
            data_out_11 <= data_stack[10];
            data_out_12 <= data_stack[11];
            data_out_13 <= data_stack[12];
            data_out_14 <= data_stack[13];
            data_out_15 <= data_stack[14];
            data_out_16 <= data_stack[15];
            data_out_17 <= data_stack[16];
            data_out_18 <= data_stack[17];
            data_out_19 <= data_stack[18];
            data_out_20 <= data_stack[19];
            data_out_21 <= data_stack[20];
            data_out_22 <= data_stack[21];
            data_out_23 <= data_stack[22];
            data_out_24 <= data_stack[23];
            data_out_25 <= data_stack[24];
            data_out_26 <= data_stack[25];
            data_out_27 <= data_stack[26];
            data_out_28 <= data_stack[27];
            data_out_29 <= data_stack[28];
            data_out_30 <= data_stack[29];
            data_out_31 <= data_stack[30];
            data_out_32 <= data_stack[31];
            data_out_33 <= data_stack[32];
            data_out_34 <= data_stack[33];
            data_out_35 <= data_stack[34];
            data_out_36 <= data_stack[35];
            data_out_37 <= data_stack[36];
            data_out_38 <= data_stack[37];
            data_out_39 <= data_stack[38];
            data_out_40 <= data_stack[39];
            data_out_41 <= data_stack[40];
            data_out_42 <= data_stack[41];
            data_out_43 <= data_stack[42];
            data_out_44 <= data_stack[43];
            data_out_45 <= data_stack[44];
            data_out_46 <= data_stack[45];
            data_out_47 <= data_stack[46];
            data_out_48 <= data_stack[47];
            data_out_49 <= data_stack[48];
            data_out_50 <= data_stack[49];
            data_out_51 <= data_stack[50];
            data_out_52 <= data_stack[51];
            data_out_53 <= data_stack[52];
            data_out_54 <= data_stack[53];
            data_out_55 <= data_stack[54];
            data_out_56 <= data_stack[55];
            data_out_57 <= data_stack[56];
            data_out_58 <= data_stack[57];
            data_out_59 <= data_stack[58];
            data_out_60 <= data_stack[59];
            data_out_61 <= data_stack[60];
            data_out_62 <= data_stack[61];
            data_out_63 <= data_stack[62];
        end
        else
        begin
            data_stack[i] <= data_stack[i];
        end
end

endmodule

testbenchs/testbench_fifo.sv
`timescale 1ns / 1ps

////////////////////////////////////////////////////////////////////////////////
// Company: 
// Engineer:
//
// Create Date:   21:58:19 02/06/2026
// Design Name:   rng_fifo
// Module Name:   testbench.v
// Project Name:  rng
// Target Device:  
// Tool versions:  
// Description: 
//
// Verilog Test Fixture created by ISE for module: rng_fifo
//
// Dependencies:
// 
// Revision:
// Revision 0.01 - File Created
// Additional Comments:
// 
////////////////////////////////////////////////////////////////////////////////

module testbench;

    localparam DEPTH         = 72;                       //Profundidade
    localparam T_DEPTH       = (DEPTH-1);                //Profundidade real
    localparam WIDTH         = 8;                        //Largura
    localparam T_WIDTH       = (WIDTH-1);                //Largura "real" para uso vetorial
    localparam SEED_TOT_NUMB = 64;                       //Total de números das seeds agrupados
    localparam T_SEED_T_NUMB = (SEED_TOT_NUMB-1);        //Total de números das seeds agrupados
    localparam COUNT_WIDTH   = $clog2(SEED_TOT_NUMB);    //Largura do contador de ciclos
    localparam T_COUNT_WID   = (COUNT_WIDTH-1);          //Largura "real" para uso vetorial

	// Inputs
	logic clk_i;
	logic write;
	logic rst_i;
	logic [T_WIDTH:0] data_in;

	//Variável de sustentação do looping
	integer i;

	// Instantiate the Unit Under Test (UUT)
	rng_fifo uut (
		.clk_i(clk_i), 
		.write(write), 
		.rst_i(rst_i), 
		.data_in(data_in)
	);

    initial 
        begin: Clock_generator
          clk_i = 0;
          forever #5 clk_i = ~clk_i;
        end

	function [T_WIDTH:0] vlr;
		input [T_WIDTH:0] value;
		begin
			data_in = value;
		end
	endfunction

	task reset;
		rst_i = 0;
		#10;
		rst_i = 1;
		#10;
	endtask 

	task wr;
		#50;
		write = 1'b1;
		#50;
		write = 1'b0;
	endtask 

	initial 
        begin
			//-------------------------------------------------
			reset();
			//-------------------------------------------------
			for (i = 0; i < SEED_TOT_NUMB; i = i + 1)
				begin
					vlr(i);
					wr();
				end
			//-------------------------------------------------
			#500;
			$finish;
        end
      
    initial 
        begin: Wavedump
                $dumpfile("../waveforms/fifo.vcd");
            $dumpvars(0, uut);
        end

endmodule

waveforms/fifo.vcd
$date
	Sat Feb  7 17:58:40 2026
$end
$version
	Icarus Verilog
$end
$timescale
	1ps
$end
$scope module testbench $end
$scope module uut $end
$var wire 1 ! clk_i $end
$var wire 8 " data_in [7:0] $end
$var wire 1 # rst_i $end
$var wire 1 $ write $end
$var wire 1 % write_pulse $end
$var parameter 32 & COUNT_WIDTH $end
$var parameter 32 ' DEPTH $end
$var parameter 32 ( SEED_TOT_NUMB $end
$var parameter 33 ) T_COUNT_WID $end
$var parameter 33 * T_DEPTH $end
$var parameter 33 + T_WIDTH $end
$var parameter 32 , WIDTH $end
$var parameter 32 - await $end
$var parameter 32 . write_data $end
$var reg 6 / cycle_count [5:0] $end
$var reg 8 0 data_out_00 [7:0] $end
$var reg 8 1 data_out_01 [7:0] $end
$var reg 8 2 data_out_02 [7:0] $end
$var reg 8 3 data_out_03 [7:0] $end
$var reg 8 4 data_out_04 [7:0] $end
$var reg 8 5 data_out_05 [7:0] $end
$var reg 8 6 data_out_06 [7:0] $end
$var reg 8 7 data_out_07 [7:0] $end
$var reg 8 8 data_out_08 [7:0] $end
$var reg 8 9 data_out_09 [7:0] $end
$var reg 8 : data_out_10 [7:0] $end
$var reg 8 ; data_out_11 [7:0] $end
$var reg 8 < data_out_12 [7:0] $end
$var reg 8 = data_out_13 [7:0] $end
$var reg 8 > data_out_14 [7:0] $end
$var reg 8 ? data_out_15 [7:0] $end
$var reg 8 @ data_out_16 [7:0] $end
$var reg 8 A data_out_17 [7:0] $end
$var reg 8 B data_out_18 [7:0] $end
$var reg 8 C data_out_19 [7:0] $end
$var reg 8 D data_out_20 [7:0] $end
$var reg 8 E data_out_21 [7:0] $end
$var reg 8 F data_out_22 [7:0] $end
$var reg 8 G data_out_23 [7:0] $end
$var reg 8 H data_out_24 [7:0] $end
$var reg 8 I data_out_25 [7:0] $end
$var reg 8 J data_out_26 [7:0] $end
$var reg 8 K data_out_27 [7:0] $end
$var reg 8 L data_out_28 [7:0] $end
$var reg 8 M data_out_29 [7:0] $end
$var reg 8 N data_out_30 [7:0] $end
$var reg 8 O data_out_31 [7:0] $end
$var reg 8 P data_out_32 [7:0] $end
$var reg 8 Q data_out_33 [7:0] $end
$var reg 8 R data_out_34 [7:0] $end
$var reg 8 S data_out_35 [7:0] $end
$var reg 8 T data_out_36 [7:0] $end
$var reg 8 U data_out_37 [7:0] $end
$var reg 8 V data_out_38 [7:0] $end
$var reg 8 W data_out_39 [7:0] $end
$var reg 8 X data_out_40 [7:0] $end
$var reg 8 Y data_out_41 [7:0] $end
$var reg 8 Z data_out_42 [7:0] $end
$var reg 8 [ data_out_43 [7:0] $end
$var reg 8 \ data_out_44 [7:0] $end
$var reg 8 ] data_out_45 [7:0] $end
$var reg 8 ^ data_out_46 [7:0] $end
$var reg 8 _ data_out_47 [7:0] $end
$var reg 8 ` data_out_48 [7:0] $end
$var reg 8 a data_out_49 [7:0] $end
$var reg 8 b data_out_50 [7:0] $end
$var reg 8 c data_out_51 [7:0] $end
$var reg 8 d data_out_52 [7:0] $end
$var reg 8 e data_out_53 [7:0] $end
$var reg 8 f data_out_54 [7:0] $end
$var reg 8 g data_out_55 [7:0] $end
$var reg 8 h data_out_56 [7:0] $end
$var reg 8 i data_out_57 [7:0] $end
$var reg 8 j data_out_58 [7:0] $end
$var reg 8 k data_out_59 [7:0] $end
$var reg 8 l data_out_60 [7:0] $end
$var reg 8 m data_out_61 [7:0] $end
$var reg 8 n data_out_62 [7:0] $end
$var reg 8 o data_out_63 [7:0] $end
$var reg 1 p next_state $end
$var reg 1 q write_d $end
$var integer 32 r i [31:0] $end
$upscope $end
$upscope $end
$enddefinitions $end
$comment Show the parameter values. $end
$dumpall
b1 .
b0 -
b1000 ,
b111 +
b1000111 *
b101 )
b1000000 (
b1001000 '
b110 &
$end
#0
$dumpvars
b1000000 r
0q
xp
b0 o
b0 n
b0 m
b0 l
b0 k
b0 j
b0 i
b0 h
b0 g
b0 f
b0 e
b0 d
b0 c
b0 b
b0 a
b0 `
b0 _
b0 ^
b0 ]
b0 \
b0 [
b0 Z
b0 Y
b0 X
b0 W
b0 V
b0 U
b0 T
b0 S
b0 R
b0 Q
b0 P
b0 O
b0 N
b0 M
b0 L
b0 K
b0 J
b0 I
b0 H
b0 G
b0 F
b0 E
b0 D
b0 C
b0 B
b0 A
b0 @
b0 ?
b0 >
b0 =
b0 <
b0 ;
b0 :
b0 9
b0 8
b0 7
b0 6
b0 5
b0 4
b0 3
b0 2
b0 1
b0 0
b0 /
x%
x$
0#
bx "
0!
$end
#5000
b1000000 r
1!
#10000
0!
1#
#15000
0p
xq
1!
#20000
0!
b0 "
#25000
1!
#30000
0!
#35000
1!
#40000
0!
#45000
1!
#50000
0!
#55000
1!
#60000
0!
#65000
1!
#70000
0!
1$
#75000
0%
1q
1!
#80000
0!
#85000
1!
#90000
0!
#95000
1!
#100000
0!
#105000
1!
#110000
0!
#115000
1!
#120000
0!
b1 "
0$
#125000
0q
1!
#130000
0!
#135000
1!
#140000
0!
#145000
1!
#150000
0!
#155000
1!
#160000
0!
#165000
1!
#170000
1%
0!
1$
#175000
0%
b1 0
b1 /
1p
1q
b0 r
1!
#180000
0!
#185000
0p
1!
#190000
0!
#195000
1!
#200000
0!
#205000
1!
#210000
0!
#215000
1!
#220000
0!
b10 "
0$
#225000
0q
1!
#230000
0!
#235000
1!
#240000
0!
#245000
1!
#250000
0!
#255000
1!
#260000
0!
#265000
1!
#270000
1%
0!
1$
#275000
0%
b1 1
b10 0
b10 /
1p
1q
b0 r
1!
#280000
0!
#285000
0p
1!
#290000
0!
#295000
1!
#300000
0!
#305000
1!
#310000
0!
#315000
1!
#320000
0!
b11 "
0$
#325000
0q
1!
#330000
0!
#335000
1!
#340000
0!
#345000
1!
#350000
0!
#355000
1!
#360000
0!
#365000
1!
#370000
1%
0!
1$
#375000
0%
b1 2
b10 1
b11 0
b11 /
1p
1q
b0 r
1!
#380000
0!
#385000
0p
1!
#390000
0!
#395000
1!
#400000
0!
#405000
1!
#410000
0!
#415000
1!
#420000
0!
b100 "
0$
#425000
0q
1!
#430000
0!
#435000
1!
#440000
0!
#445000
1!
#450000
0!
#455000
1!
#460000
0!
#465000
1!
#470000
1%
0!
1$
#475000
0%
b1 3
b10 2
b11 1
b100 0
b100 /
1p
1q
b0 r
1!
#480000
0!
#485000
0p
1!
#490000
0!
#495000
1!
#500000
0!
#505000
1!
#510000
0!
#515000
1!
#520000
0!
b101 "
0$
#525000
0q
1!
#530000
0!
#535000
1!
#540000
0!
#545000
1!
#550000
0!
#555000
1!
#560000
0!
#565000
1!
#570000
1%
0!
1$
#575000
0%
b1 4
b10 3
b11 2
b100 1
b101 0
b101 /
1p
1q
b0 r
1!
#580000
0!
#585000
0p
1!
#590000
0!
#595000
1!
#600000
0!
#605000
1!
#610000
0!
#615000
1!
#620000
0!
b110 "
0$
#625000
0q
1!
#630000
0!
#635000
1!
#640000
0!
#645000
1!
#650000
0!
#655000
1!
#660000
0!
#665000
1!
#670000
1%
0!
1$
#675000
0%
b1 5
b10 4
b11 3
b100 2
b101 1
b110 0
b110 /
1p
1q
b0 r
1!
#680000
0!
#685000
0p
1!
#690000
0!
#695000
1!
#700000
0!
#705000
1!
#710000
0!
#715000
1!
#720000
0!
b111 "
0$
#725000
0q
1!
#730000
0!
#735000
1!
#740000
0!
#745000
1!
#750000
0!
#755000
1!
#760000
0!
#765000
1!
#770000
1%
0!
1$
#775000
0%
b1 6
b10 5
b11 4
b100 3
b101 2
b110 1
b111 0
b111 /
1p
1q
b0 r
1!
#780000
0!
#785000
0p
1!
#790000
0!
#795000
1!
#800000
0!
#805000
1!
#810000
0!
#815000
1!
#820000
0!
b1000 "
0$
#825000
0q
1!
#830000
0!
#835000
1!
#840000
0!
#845000
1!
#850000
0!
#855000
1!
#860000
0!
#865000
1!
#870000
1%
0!
1$
#875000
0%
b1 7
b10 6
b11 5
b100 4
b101 3
b110 2
b111 1
b1000 0
b1000 /
1p
1q
b0 r
1!
#880000
0!
#885000
0p
1!
#890000
0!
#895000
1!
#900000
0!
#905000
1!
#910000
0!
#915000
1!
#920000
0!
b1001 "
0$
#925000
0q
1!
#930000
0!
#935000
1!
#940000
0!
#945000
1!
#950000
0!
#955000
1!
#960000
0!
#965000
1!
#970000
1%
0!
1$
#975000
0%
b1 8
b10 7
b11 6
b100 5
b101 4
b110 3
b111 2
b1000 1
b1001 0
b1001 /
1p
1q
b0 r
1!
#980000
0!
#985000
0p
1!
#990000
0!
#995000
1!
#1000000
0!
#1005000
1!
#1010000
0!
#1015000
1!
#1020000
0!
b1010 "
0$
#1025000
0q
1!
#1030000
0!
#1035000
1!
#1040000
0!
#1045000
1!
#1050000
0!
#1055000
1!
#1060000
0!
#1065000
1!
#1070000
1%
0!
1$
#1075000
0%
b1 9
b10 8
b11 7
b100 6
b101 5
b110 4
b111 3
b1000 2
b1001 1
b1010 0
b1010 /
1p
1q
b0 r
1!
#1080000
0!
#1085000
0p
1!
#1090000
0!
#1095000
1!
#1100000
0!
#1105000
1!
#1110000
0!
#1115000
1!
#1120000
0!
b1011 "
0$
#1125000
0q
1!
#1130000
0!
#1135000
1!
#1140000
0!
#1145000
1!
#1150000
0!
#1155000
1!
#1160000
0!
#1165000
1!
#1170000
1%
0!
1$
#1175000
0%
b1 :
b10 9
b11 8
b100 7
b101 6
b110 5
b111 4
b1000 3
b1001 2
b1010 1
b1011 0
b1011 /
1p
1q
b0 r
1!
#1180000
0!
#1185000
0p
1!
#1190000
0!
#1195000
1!
#1200000
0!
#1205000
1!
#1210000
0!
#1215000
1!
#1220000
0!
b1100 "
0$
#1225000
0q
1!
#1230000
0!
#1235000
1!
#1240000
0!
#1245000
1!
#1250000
0!
#1255000
1!
#1260000
0!
#1265000
1!
#1270000
1%
0!
1$
#1275000
0%
b1 ;
b10 :
b11 9
b100 8
b101 7
b110 6
b111 5
b1000 4
b1001 3
b1010 2
b1011 1
b1100 0
b1100 /
1p
1q
b0 r
1!
#1280000
0!
#1285000
0p
1!
#1290000
0!
#1295000
1!
#1300000
0!
#1305000
1!
#1310000
0!
#1315000
1!
#1320000
0!
b1101 "
0$
#1325000
0q
1!
#1330000
0!
#1335000
1!
#1340000
0!
#1345000
1!
#1350000
0!
#1355000
1!
#1360000
0!
#1365000
1!
#1370000
1%
0!
1$
#1375000
0%
b1 <
b10 ;
b11 :
b100 9
b101 8
b110 7
b111 6
b1000 5
b1001 4
b1010 3
b1011 2
b1100 1
b1101 0
b1101 /
1p
1q
b0 r
1!
#1380000
0!
#1385000
0p
1!
#1390000
0!
#1395000
1!
#1400000
0!
#1405000
1!
#1410000
0!
#1415000
1!
#1420000
0!
b1110 "
0$
#1425000
0q
1!
#1430000
0!
#1435000
1!
#1440000
0!
#1445000
1!
#1450000
0!
#1455000
1!
#1460000
0!
#1465000
1!
#1470000
1%
0!
1$
#1475000
0%
b1 =
b10 <
b11 ;
b100 :
b101 9
b110 8
b111 7
b1000 6
b1001 5
b1010 4
b1011 3
b1100 2
b1101 1
b1110 0
b1110 /
1p
1q
b0 r
1!
#1480000
0!
#1485000
0p
1!
#1490000
0!
#1495000
1!
#1500000
0!
#1505000
1!
#1510000
0!
#1515000
1!
#1520000
0!
b1111 "
0$
#1525000
0q
1!
#1530000
0!
#1535000
1!
#1540000
0!
#1545000
1!
#1550000
0!
#1555000
1!
#1560000
0!
#1565000
1!
#1570000
1%
0!
1$
#1575000
0%
b1 >
b10 =
b11 <
b100 ;
b101 :
b110 9
b111 8
b1000 7
b1001 6
b1010 5
b1011 4
b1100 3
b1101 2
b1110 1
b1111 0
b1111 /
1p
1q
b0 r
1!
#1580000
0!
#1585000
0p
1!
#1590000
0!
#1595000
1!
#1600000
0!
#1605000
1!
#1610000
0!
#1615000
1!
#1620000
0!
b10000 "
0$
#1625000
0q
1!
#1630000
0!
#1635000
1!
#1640000
0!
#1645000
1!
#1650000
0!
#1655000
1!
#1660000
0!
#1665000
1!
#1670000
1%
0!
1$
#1675000
0%
b1 ?
b10 >
b11 =
b100 <
b101 ;
b110 :
b111 9
b1000 8
b1001 7
b1010 6
b1011 5
b1100 4
b1101 3
b1110 2
b1111 1
b10000 0
b10000 /
1p
1q
b0 r
1!
#1680000
0!
#1685000
0p
1!
#1690000
0!
#1695000
1!
#1700000
0!
#1705000
1!
#1710000
0!
#1715000
1!
#1720000
0!
b10001 "
0$
#1725000
0q
1!
#1730000
0!
#1735000
1!
#1740000
0!
#1745000
1!
#1750000
0!
#1755000
1!
#1760000
0!
#1765000
1!
#1770000
1%
0!
1$
#1775000
0%
b1 @
b10 ?
b11 >
b100 =
b101 <
b110 ;
b111 :
b1000 9
b1001 8
b1010 7
b1011 6
b1100 5
b1101 4
b1110 3
b1111 2
b10000 1
b10001 0
b10001 /
1p
1q
b0 r
1!
#1780000
0!
#1785000
0p
1!
#1790000
0!
#1795000
1!
#1800000
0!
#1805000
1!
#1810000
0!
#1815000
1!
#1820000
0!
b10010 "
0$
#1825000
0q
1!
#1830000
0!
#1835000
1!
#1840000
0!
#1845000
1!
#1850000
0!
#1855000
1!
#1860000
0!
#1865000
1!
#1870000
1%
0!
1$
#1875000
0%
b1 A
b10 @
b11 ?
b100 >
b101 =
b110 <
b111 ;
b1000 :
b1001 9
b1010 8
b1011 7
b1100 6
b1101 5
b1110 4
b1111 3
b10000 2
b10001 1
b10010 0
b10010 /
1p
1q
b0 r
1!
#1880000
0!
#1885000
0p
1!
#1890000
0!
#1895000
1!
#1900000
0!
#1905000
1!
#1910000
0!
#1915000
1!
#1920000
0!
b10011 "
0$
#1925000
0q
1!
#1930000
0!
#1935000
1!
#1940000
0!
#1945000
1!
#1950000
0!
#1955000
1!
#1960000
0!
#1965000
1!
#1970000
1%
0!
1$
#1975000
0%
b1 B
b10 A
b11 @
b100 ?
b101 >
b110 =
b111 <
b1000 ;
b1001 :
b1010 9
b1011 8
b1100 7
b1101 6
b1110 5
b1111 4
b10000 3
b10001 2
b10010 1
b10011 0
b10011 /
1p
1q
b0 r
1!
#1980000
0!
#1985000
0p
1!
#1990000
0!
#1995000
1!
#2000000
0!
#2005000
1!
#2010000
0!
#2015000
1!
#2020000
0!
b10100 "
0$
#2025000
0q
1!
#2030000
0!
#2035000
1!
#2040000
0!
#2045000
1!
#2050000
0!
#2055000
1!
#2060000
0!
#2065000
1!
#2070000
1%
0!
1$
#2075000
0%
b1 C
b10 B
b11 A
b100 @
b101 ?
b110 >
b111 =
b1000 <
b1001 ;
b1010 :
b1011 9
b1100 8
b1101 7
b1110 6
b1111 5
b10000 4
b10001 3
b10010 2
b10011 1
b10100 0
b10100 /
1p
1q
b0 r
1!
#2080000
0!
#2085000
0p
1!
#2090000
0!
#2095000
1!
#2100000
0!
#2105000
1!
#2110000
0!
#2115000
1!
#2120000
0!
b10101 "
0$
#2125000
0q
1!
#2130000
0!
#2135000
1!
#2140000
0!
#2145000
1!
#2150000
0!
#2155000
1!
#2160000
0!
#2165000
1!
#2170000
1%
0!
1$
#2175000
0%
b1 D
b10 C
b11 B
b100 A
b101 @
b110 ?
b111 >
b1000 =
b1001 <
b1010 ;
b1011 :
b1100 9
b1101 8
b1110 7
b1111 6
b10000 5
b10001 4
b10010 3
b10011 2
b10100 1
b10101 0
b10101 /
1p
1q
b0 r
1!
#2180000
0!
#2185000
0p
1!
#2190000
0!
#2195000
1!
#2200000
0!
#2205000
1!
#2210000
0!
#2215000
1!
#2220000
0!
b10110 "
0$
#2225000
0q
1!
#2230000
0!
#2235000
1!
#2240000
0!
#2245000
1!
#2250000
0!
#2255000
1!
#2260000
0!
#2265000
1!
#2270000
1%
0!
1$
#2275000
0%
b1 E
b10 D
b11 C
b100 B
b101 A
b110 @
b111 ?
b1000 >
b1001 =
b1010 <
b1011 ;
b1100 :
b1101 9
b1110 8
b1111 7
b10000 6
b10001 5
b10010 4
b10011 3
b10100 2
b10101 1
b10110 0
b10110 /
1p
1q
b0 r
1!
#2280000
0!
#2285000
0p
1!
#2290000
0!
#2295000
1!
#2300000
0!
#2305000
1!
#2310000
0!
#2315000
1!
#2320000
0!
b10111 "
0$
#2325000
0q
1!
#2330000
0!
#2335000
1!
#2340000
0!
#2345000
1!
#2350000
0!
#2355000
1!
#2360000
0!
#2365000
1!
#2370000
1%
0!
1$
#2375000
0%
b1 F
b10 E
b11 D
b100 C
b101 B
b110 A
b111 @
b1000 ?
b1001 >
b1010 =
b1011 <
b1100 ;
b1101 :
b1110 9
b1111 8
b10000 7
b10001 6
b10010 5
b10011 4
b10100 3
b10101 2
b10110 1
b10111 0
b10111 /
1p
1q
b0 r
1!
#2380000
0!
#2385000
0p
1!
#2390000
0!
#2395000
1!
#2400000
0!
#2405000
1!
#2410000
0!
#2415000
1!
#2420000
0!
b11000 "
0$
#2425000
0q
1!
#2430000
0!
#2435000
1!
#2440000
0!
#2445000
1!
#2450000
0!
#2455000
1!
#2460000
0!
#2465000
1!
#2470000
1%
0!
1$
#2475000
0%
b1 G
b10 F
b11 E
b100 D
b101 C
b110 B
b111 A
b1000 @
b1001 ?
b1010 >
b1011 =
b1100 <
b1101 ;
b1110 :
b1111 9
b10000 8
b10001 7
b10010 6
b10011 5
b10100 4
b10101 3
b10110 2
b10111 1
b11000 0
b11000 /
1p
1q
b0 r
1!
#2480000
0!
#2485000
0p
1!
#2490000
0!
#2495000
1!
#2500000
0!
#2505000
1!
#2510000
0!
#2515000
1!
#2520000
0!
b11001 "
0$
#2525000
0q
1!
#2530000
0!
#2535000
1!
#2540000
0!
#2545000
1!
#2550000
0!
#2555000
1!
#2560000
0!
#2565000
1!
#2570000
1%
0!
1$
#2575000
0%
b1 H
b10 G
b11 F
b100 E
b101 D
b110 C
b111 B
b1000 A
b1001 @
b1010 ?
b1011 >
b1100 =
b1101 <
b1110 ;
b1111 :
b10000 9
b10001 8
b10010 7
b10011 6
b10100 5
b10101 4
b10110 3
b10111 2
b11000 1
b11001 0
b11001 /
1p
1q
b0 r
1!
#2580000
0!
#2585000
0p
1!
#2590000
0!
#2595000
1!
#2600000
0!
#2605000
1!
#2610000
0!
#2615000
1!
#2620000
0!
b11010 "
0$
#2625000
0q
1!
#2630000
0!
#2635000
1!
#2640000
0!
#2645000
1!
#2650000
0!
#2655000
1!
#2660000
0!
#2665000
1!
#2670000
1%
0!
1$
