src/rng_selector.v
//////////////////////////////////////////////////////////////////////////////////
// Company: 
// Engineer: 
// 
// Create Date:    16:19:00 02/01/2026 
// Design Name: 
// Module Name:    rng_selector
// Project Name: 
// Target Devices: 
// Tool versions: 
// Description: 
//
// Dependencies: 
//
// Revision: 
// Revision 0.01 - File Created
// Additional Comments: 
//
//////////////////////////////////////////////////////////////////////////////////

module rng_selector
#(
    parameter DEPTH         = 72,                       //Profundidade
    parameter T_DEPTH       = (DEPTH-1),                //Profundidade real
    parameter WIDTH         = 3,                        //Largura
    parameter T_WIDTH       = (WIDTH-1),                //Largura "real" para uso vetorial
    parameter SEED_TOT_NUMB = 12,                        //Total de números das seeds agrupados
    parameter SD_T_TOT_NUMB = (SEED_TOT_NUMB - 1),      //Total "real" de números das seeds agrupados
    parameter COUNT_WIDTH   = $clog2(SEED_TOT_NUMB),    //Largura do contador de ciclos
    parameter T_COUNT_WID   = (COUNT_WIDTH-1)           //Largura "real" para uso vetorial
)
(
    input clk_i,
    input start_i,
    input rst_i,
    output reg [1:0] seed_sel_o
);

reg [1:0] seed_s;

    localparam seed_1 = 2'b00;
    localparam seed_2 = 2'b01;
    localparam seed_3 = 2'b10;
    localparam seed_4 = 2'b11;

always@(posedge clk_i or negedge rst_i)
    begin
        if(!rst_i)
            begin
                seed_s <= 0;
            end
        else
            begin
                seed_s <= seed_s + 1'b1;
            end
    end

always@(*)
    begin
        seed_sel_o = seed_s;
    end
endmodule

testbenchs/testbench_sel.sv
`timescale 1ns / 1ps

////////////////////////////////////////////////////////////////////////////////
// Company: 
// Engineer:
//
// Create Date:   21:58:19 02/06/2026
// Design Name:   rng_fifo
// Module Name:   testbench.v
// Project Name:  rng
// Target Device:  
// Tool versions:  
// Description: 
//
// Verilog Test Fixture created by ISE for module: rng_fifo
//
// Dependencies:
// 
// Revision:
// Revision 0.01 - File Created
// Additional Comments:
// 
////////////////////////////////////////////////////////////////////////////////

module testbench_sel;

    localparam DEPTH         = 72;                       //Profundidade
    localparam T_DEPTH       = (DEPTH-1);                //Profundidade real
    localparam WIDTH         = 8;                        //Largura
    localparam T_WIDTH       = (WIDTH-1);                //Largura "real" para uso vetorial
    localparam SEED_TOT_NUMB = 64;                       //Total de números das seeds agrupados
    localparam T_SEED_T_NUMB = (SEED_TOT_NUMB-1);        //Total de números das seeds agrupados
    localparam COUNT_WIDTH   = $clog2(SEED_TOT_NUMB);    //Largura do contador de ciclos
    localparam T_COUNT_WID   = (COUNT_WIDTH-1);          //Largura "real" para uso vetorial

	// Inputs
	logic clk_i;
	logic start_i;
	logic rst_i;
	logic [1:0] seed_sel_o;

	//Variável de sustentação do looping
	integer i;

	// Instantiate the Unit Under Test (UUT)
	rng_selector uut 
					(
						.clk_i(clk_i), 
						.start_i(start_i), 
						.rst_i(rst_i), 
						.seed_sel_o(seed_sel_o)
					);

	initial
		begin: Clock_generator
			clk_i = 0;
			forever #5 clk_i = ~clk_i;
		end

	task reset;
		rst_i = 0;
		#10;
		rst_i = 1;
		#10;
	endtask 

	task wr;
		#50;
		start_i = 1'b1;
		#50;
		start_i = 1'b0;
	endtask 

	initial 
        begin
			//-------------------------------------------------
			reset();
			//-------------------------------------------------
			start_i = 1;
			//-------------------------------------------------
			#500;
			$finish;
        end
      
    initial 
        begin: Wavedump
                $dumpfile("../waveforms/sel.vcd");
            $dumpvars(0, uut);
        end

endmodule

waveforms/sel.vcd
$date
	Thu Feb 12 09:45:15 2026
$end
$version
	Icarus Verilog
$end
$timescale
	1ps
$end
$scope module testbench_sel $end
$scope module uut $end
$var wire 1 ! clk_i $end
$var wire 1 " rst_i $end
$var wire 2 # seed_sel_o [1:0] $end
$var wire 1 $ start_i $end
$var parameter 2 % seed_1 $end
$var parameter 2 & seed_2 $end
$var parameter 2 ' seed_3 $end
$var parameter 2 ( seed_4 $end
$var reg 2 ) seed_s [1:0] $end
$upscope $end
$upscope $end
$enddefinitions $end
$comment Show the parameter values. $end
$dumpall
b11 (
b10 '
b1 &
b0 %
$end
#0
$dumpvars
b0 )
x$
b0 #
0"
0!
$end
#5000
1!
#10000
0!
1"
#15000
b1 #
b1 )
1!
#20000
0!
1$
#25000
b10 #
b10 )
1!
#30000
0!
#35000
b11 #
b11 )
1!
#40000
0!
#45000
b0 #
b0 )
1!
#50000
0!
#55000
b1 #
b1 )
1!
#60000
0!
#65000
b10 #
b10 )
1!
#70000
0!
#75000
b11 #
b11 )
1!
#80000
0!
#85000
b0 #
b0 )
1!
#90000
0!
#95000
b1 #
b1 )
1!
#100000
0!
#105000
b10 #
b10 )
1!
#110000
0!
#115000
b11 #
b11 )
1!
#120000
0!
#125000
b0 #
b0 )
1!
#130000
0!
#135000
b1 #
b1 )
1!
#140000
0!
#145000
b10 #
b10 )
1!
#150000
0!
#155000
b11 #
b11 )
1!
#160000
0!
#165000
b0 #
b0 )
1!
#170000
0!
#175000
b1 #
b1 )
1!
#180000
0!
#185000
b10 #
b10 )
1!
#190000
0!
#195000
b11 #
b11 )
1!
#200000
0!
#205000
b0 #
b0 )
1!
#210000
0!
#215000
b1 #
b1 )
1!
#220000
0!
#225000
b10 #
b10 )
1!
#230000
0!
#235000
b11 #
b11 )
1!
#240000
0!
#245000
b0 #
b0 )
1!
#250000
0!
#255000
b1 #
b1 )
1!
#260000
0!
#265000
b10 #
b10 )
1!
#270000
0!
#275000
b11 #
b11 )
1!
#280000
0!
#285000
b0 #
b0 )
1!
#290000
0!
#295000
b1 #
b1 )
1!
#300000
0!
#305000
b10 #
b10 )
1!
#310000
0!
#315000
b11 #
b11 )
1!
#320000
0!
#325000
b0 #
b0 )
1!
#330000
0!
#335000
b1 #
b1 )
1!
#340000
0!
#345000
b10 #
b10 )
1!
#350000
0!
#355000
b11 #
b11 )
1!
#360000
0!
#365000
b0 #
b0 )
1!
#370000
0!
#375000
b1 #
b1 )
1!
#380000
0!
#385000
b10 #
b10 )
1!
#390000
0!
#395000
b11 #
b11 )
1!
#400000
0!
#405000
b0 #
b0 )
1!
#410000
0!
#415000
b1 #
b1 )
1!
#420000
0!
#425000
b10 #
b10 )
1!
#430000
0!
#435000
b11 #
b11 )
1!
#440000
0!
#445000
b0 #
b0 )
1!
#450000
0!
#455000
b1 #
b1 )
1!
#460000
0!
#465000
b10 #
b10 )
1!
#470000
0!
#475000
b11 #
b11 )
1!
#480000
0!
#485000
b0 #
b0 )
1!
#490000
0!
#495000
b1 #
b1 )
1!
#500000
0!
#505000
b10 #
b10 )
1!
#510000
0!
#515000
b11 #
b11 )
1!
